<?xml version='1.0' encoding='UTF-8'?>
<annotation>
   <folder>ex02</folder>
   <filename>ex02_writer0001.jpg</filename>
   <size>
      <width>2821</width>
      <height>2000</height>
   </size>
   <object>
      <name>OK]</name>
      <degree>-2.66</degree>
      <direction>lr</direction>
      <bndbox>
         <xmin>1973</xmin>
         <ymin>1244</ymin>
         <xmax>2059</xmax>
         <ymax>1301</ymax>
      </bndbox>
   </object>
   <object>
      <name>[NOT</name>
      <degree>0.92</degree>
      <direction>lr</direction>
      <bndbox>
         <xmin>1836</xmin>
         <ymin>1241</ymin>
         <xmax>1964</xmax>
         <ymax>1292</ymax>
      </bndbox>
   </object>
   <object>
      <name>[ok]</name>
      <degree>1.19</degree>
      <direction>lr</direction>
      <bndbox>
         <xmin>1690</xmin>
         <ymin>1869</ymin>
         <xmax>1775</xmax>
         <ymax>1917</ymax>
      </bndbox>
   </object>
   <object>
      <name>recommendation</name>
      <degree>-0.59</degree>
      <direction>lr</direction>
      <bndbox>
         <xmin>1379</xmin>
         <ymin>1870</ymin>
         <xmax>1690</xmax>
         <ymax>1915</ymax>
      </bndbox>
   </object>
   <object>
      <name>process</name>
      <degree>-0.83</degree>
      <direction>lr</direction>
      <bndbox>
         <xmin>2211</xmin>
         <ymin>1837</ymin>
         <xmax>2360</xmax>
         <ymax>1885</ymax>
      </bndbox>
   </object>
   <object>
      <name>settlement</name>
      <degree>0.28</degree>
      <direction>lr</direction>
      <bndbox>
         <xmin>1495</xmin>
         <ymin>1823</ymin>
         <xmax>1722</xmax>
         <ymax>1875</ymax>
      </bndbox>
   </object>
   <object>
      <name>handling</name>
      <degree>0</degree>
      <direction>lr</direction>
      <bndbox>
         <xmin>2211</xmin>
         <ymin>1791</ymin>
         <xmax>2388</xmax>
         <ymax>1852</ymax>
      </bndbox>
   </object>
   <object>
      <name>senior</name>
      <degree>90.81</degree>
      <direction>bt</direction>
      <bndbox>
         <xmin>218</xmin>
         <ymin>1732</ymin>
         <xmax>263</xmax>
         <ymax>1892</ymax>
      </bndbox>
   </object>
   <object>
      <name>proceed</name>
      <degree>0.19</degree>
      <direction>lr</direction>
      <bndbox>
         <xmin>2204</xmin>
         <ymin>1748</ymin>
         <xmax>2373</xmax>
         <ymax>1802</ymax>
      </bndbox>
   </object>
   <object>
      <name>OK</name>
      <degree>0</degree>
      <direction>lr</direction>
      <bndbox>
         <xmin>2067</xmin>
         <ymin>1741</ymin>
         <xmax>2139</xmax>
         <ymax>1786</ymax>
      </bndbox>
   </object>
   <object>
      <name>recommendation</name>
      <degree>2.11</degree>
      <direction>lr</direction>
      <bndbox>
         <xmin>1681</xmin>
         <ymin>1729</ymin>
         <xmax>2020</xmax>
         <ymax>1795</ymax>
      </bndbox>
   </object>
   <object>
      <name>closed</name>
      <degree>1.8</degree>
      <direction>lr</direction>
      <bndbox>
         <xmin>2493</xmin>
         <ymin>1698</ymin>
         <xmax>2630</xmax>
         <ymax>1749</ymax>
      </bndbox>
   </object>
   <object>
      <name>Settlement</name>
      <degree>0</degree>
      <direction>lr</direction>
      <bndbox>
         <xmin>1680</xmin>
         <ymin>1698</ymin>
         <xmax>1893</xmax>
         <ymax>1750</ymax>
      </bndbox>
   </object>
   <object>
      <name>office</name>
      <degree>90.0</degree>
      <direction>bt</direction>
      <bndbox>
         <xmin>258</xmin>
         <ymin>1640</ymin>
         <xmax>311</xmax>
         <ymax>1788</ymax>
      </bndbox>
   </object>
   <object>
      <name>claim</name>
      <degree>-0.67</degree>
      <direction>lr</direction>
      <bndbox>
         <xmin>2473</xmin>
         <ymin>1655</ymin>
         <xmax>2584</xmax>
         <ymax>1711</ymax>
      </bndbox>
   </object>
   <object>
      <name>the</name>
      <degree>-0.0</degree>
      <direction>lr</direction>
      <bndbox>
         <xmin>1679</xmin>
         <ymin>1653</ymin>
         <xmax>1771</xmax>
         <ymax>1702</ymax>
      </bndbox>
   </object>
   <object>
      <name>check</name>
      <degree>1.04</degree>
      <direction>lr</direction>
      <bndbox>
         <xmin>1682</xmin>
         <ymin>1598</ymin>
         <xmax>1809</xmax>
         <ymax>1655</ymax>
      </bndbox>
   </object>
   <object>
      <name>claims</name>
      <degree>87.73</degree>
      <direction>bt</direction>
      <bndbox>
         <xmin>210</xmin>
         <ymin>1530</ymin>
         <xmax>263</xmax>
         <ymax>1682</ymax>
      </bndbox>
   </object>
   <object>
      <name>OK</name>
      <degree>2.6</degree>
      <direction>lr</direction>
      <bndbox>
         <xmin>2072</xmin>
         <ymin>1553</ymin>
         <xmax>2139</xmax>
         <ymax>1596</ymax>
      </bndbox>
   </object>
   <object>
      <name>Not</name>
      <degree>1.2</degree>
      <direction>lr</direction>
      <bndbox>
         <xmin>2066</xmin>
         <ymin>1509</ymin>
         <xmax>2148</xmax>
         <ymax>1557</ymax>
      </bndbox>
   </object>
   <object>
      <name>insuarer</name>
      <degree>89.66</degree>
      <direction>bt</direction>
      <bndbox>
         <xmin>96</xmin>
         <ymin>1195</ymin>
         <xmax>177</xmax>
         <ymax>1475</ymax>
      </bndbox>
   </object>
   <object>
      <name>recommendation</name>
      <degree>0.19</degree>
      <direction>lr</direction>
      <bndbox>
         <xmin>944</xmin>
         <ymin>1297</ymin>
         <xmax>1265</xmax>
         <ymax>1349</ymax>
      </bndbox>
   </object>
   <object>
      <name>settlement</name>
      <degree>-0.25</degree>
      <direction>lr</direction>
      <bndbox>
         <xmin>999</xmin>
         <ymin>1238</ymin>
         <xmax>1245</xmax>
         <ymax>1302</ymax>
      </bndbox>
   </object>
   <object>
      <name>claim</name>
      <degree>-1.64</degree>
      <direction>lr</direction>
      <bndbox>
         <xmin>370</xmin>
         <ymin>1252</ymin>
         <xmax>473</xmax>
         <ymax>1295</ymax>
      </bndbox>
   </object>
   <object>
      <name>recommendation</name>
      <degree>-0.85</degree>
      <direction>lr</direction>
      <bndbox>
         <xmin>1836</xmin>
         <ymin>1197</ymin>
         <xmax>2112</xmax>
         <ymax>1251</ymax>
      </bndbox>
   </object>
   <object>
      <name>office</name>
      <degree>88.97</degree>
      <direction>bt</direction>
      <bndbox>
         <xmin>212</xmin>
         <ymin>1029</ymin>
         <xmax>286</xmax>
         <ymax>1205</ymax>
      </bndbox>
   </object>
   <object>
      <name>claims</name>
      <degree>88.62</degree>
      <direction>bt</direction>
      <bndbox>
         <xmin>212</xmin>
         <ymin>1260</ymin>
         <xmax>272</xmax>
         <ymax>1437</ymax>
      </bndbox>
   </object>
   <object>
      <name>settlement</name>
      <degree>-0.45</degree>
      <direction>lr</direction>
      <bndbox>
         <xmin>1833</xmin>
         <ymin>1144</ymin>
         <xmax>2030</xmax>
         <ymax>1201</ymax>
      </bndbox>
   </object>
   <object>
      <name>recommendation</name>
      <degree>-0.09</degree>
      <direction>lr</direction>
      <bndbox>
         <xmin>1206</xmin>
         <ymin>1088</ymin>
         <xmax>1542</xmax>
         <ymax>1140</ymax>
      </bndbox>
   </object>
   <object>
      <name>settlement</name>
      <degree>-0.98</degree>
      <direction>lr</direction>
      <bndbox>
         <xmin>1208</xmin>
         <ymin>1037</ymin>
         <xmax>1430</xmax>
         <ymax>1094</ymax>
      </bndbox>
   </object>
   <object>
      <name>claim</name>
      <degree>1.3</degree>
      <direction>lr</direction>
      <bndbox>
         <xmin>902</xmin>
         <ymin>1047</ymin>
         <xmax>1016</xmax>
         <ymax>1099</ymax>
      </bndbox>
   </object>
   <object>
      <name>claim</name>
      <degree>-0.0</degree>
      <direction>lr</direction>
      <bndbox>
         <xmin>590</xmin>
         <ymin>1049</ymin>
         <xmax>714</xmax>
         <ymax>1102</ymax>
      </bndbox>
   </object>
   <object>
      <name>write</name>
      <degree>-0.27</degree>
      <direction>lr</direction>
      <bndbox>
         <xmin>1207</xmin>
         <ymin>995</ymin>
         <xmax>1337</xmax>
         <ymax>1045</ymax>
      </bndbox>
   </object>
   <object>
      <name>examine</name>
      <degree>0.82</degree>
      <direction>lr</direction>
      <bndbox>
         <xmin>894</xmin>
         <ymin>998</ymin>
         <xmax>1091</xmax>
         <ymax>1047</ymax>
      </bndbox>
   </object>
   <object>
      <name>register</name>
      <degree>-0.0</degree>
      <direction>lr</direction>
      <bndbox>
         <xmin>568</xmin>
         <ymin>995</ymin>
         <xmax>745</xmax>
         <ymax>1051</ymax>
      </bndbox>
   </object>
   <object>
      <name>[examined]</name>
      <degree>1.64</degree>
      <direction>lr</direction>
      <bndbox>
         <xmin>1100</xmin>
         <ymin>924</ymin>
         <xmax>1331</xmax>
         <ymax>979</ymax>
      </bndbox>
   </object>
   <object>
      <name>claim</name>
      <degree>0.86</degree>
      <direction>lr</direction>
      <bndbox>
         <xmin>986</xmin>
         <ymin>930</ymin>
         <xmax>1101</xmax>
         <ymax>980</ymax>
      </bndbox>
   </object>
   <object>
      <name>costumer</name>
      <degree>-1.22</degree>
      <direction>lr</direction>
      <bndbox>
         <xmin>581</xmin>
         <ymin>796</ymin>
         <xmax>774</xmax>
         <ymax>845</ymax>
      </bndbox>
   </object>
   <object>
      <name>of</name>
      <degree>1.27</degree>
      <direction>lr</direction>
      <bndbox>
         <xmin>526</xmin>
         <ymin>792</ymin>
         <xmax>583</xmax>
         <ymax>842</ymax>
      </bndbox>
   </object>
   <object>
      <name>claim</name>
      <degree>3.05</degree>
      <direction>lr</direction>
      <bndbox>
         <xmin>425</xmin>
         <ymin>794</ymin>
         <xmax>523</xmax>
         <ymax>837</ymax>
      </bndbox>
   </object>
   <object>
      <name>customer</name>
      <degree>90</degree>
      <direction>bt</direction>
      <bndbox>
         <xmin>113</xmin>
         <ymin>480</ymin>
         <xmax>175</xmax>
         <ymax>689</ymax>
      </bndbox>
   </object>
</annotation>
