<?xml version="1.0" ?>
<annotation>
   <folder>ex10</folder>
   <filename>ex10_writer0012.jpg</filename>
   <size>
      <width>868</width>
      <height>630</height>
   </size>
   <object>
      <name>out</name>
      <degree>0</degree>
      <direction>lr</direction>
      <bndbox>
         <xmin>578</xmin>
         <ymin>340</ymin>
         <xmax>597</xmax>
         <ymax>352</ymax>
      </bndbox>
   </object>
   <object>
      <name>for</name>
      <degree>-1.79</degree>
      <direction>lr</direction>
      <bndbox>
         <xmin>704</xmin>
         <ymin>203</ymin>
         <xmax>726</xmax>
         <ymax>222</ymax>
      </bndbox>
   </object>
   <object>
      <name>order</name>
      <degree>0</degree>
      <direction>lr</direction>
      <bndbox>
         <xmin>542</xmin>
         <ymin>380</ymin>
         <xmax>592</xmax>
         <ymax>396</ymax>
      </bndbox>
   </object>
   <object>
      <name>offer</name>
      <degree>1.21</degree>
      <direction>lr</direction>
      <bndbox>
         <xmin>243</xmin>
         <ymin>130</ymin>
         <xmax>296</xmax>
         <ymax>148</ymax>
      </bndbox>
   </object>
   <object>
      <name>Cancellation</name>
      <degree>0.32</degree>
      <direction>lr</direction>
      <bndbox>
         <xmin>548</xmin>
         <ymin>398</ymin>
         <xmax>637</xmax>
         <ymax>412</ymax>
      </bndbox>
   </object>
   <object>
      <name>time</name>
      <degree>0</degree>
      <direction>lr</direction>
      <bndbox>
         <xmin>545</xmin>
         <ymin>340</ymin>
         <xmax>577</xmax>
         <ymax>352</ymax>
      </bndbox>
   </object>
   <object>
      <name>confirmation</name>
      <degree>-0.0</degree>
      <direction>lr</direction>
      <bndbox>
         <xmin>464</xmin>
         <ymin>294</ymin>
         <xmax>549</xmax>
         <ymax>308</ymax>
      </bndbox>
   </object>
   <object>
      <name>&gt;=3</name>
      <degree>-0.0</degree>
      <direction>lr</direction>
      <bndbox>
         <xmin>349</xmin>
         <ymin>300</ymin>
         <xmax>368</xmax>
         <ymax>315</ymax>
      </bndbox>
   </object>
   <object>
      <name>order</name>
      <degree>1.15</degree>
      <direction>lr</direction>
      <bndbox>
         <xmin>599</xmin>
         <ymin>280</ymin>
         <xmax>646</xmax>
         <ymax>294</ymax>
      </bndbox>
   </object>
   <object>
      <name>order</name>
      <degree>4.24</degree>
      <direction>lr</direction>
      <bndbox>
         <xmin>464</xmin>
         <ymin>280</ymin>
         <xmax>505</xmax>
         <ymax>296</ymax>
      </bndbox>
   </object>
   <object>
      <name>offer</name>
      <degree>0.62</degree>
      <direction>lr</direction>
      <bndbox>
         <xmin>267</xmin>
         <ymin>280</ymin>
         <xmax>319</xmax>
         <ymax>297</ymax>
      </bndbox>
   </object>
   <object>
      <name>offer</name>
      <degree>2.49</degree>
      <direction>lr</direction>
      <bndbox>
         <xmin>145</xmin>
         <ymin>278</ymin>
         <xmax>198</xmax>
         <ymax>295</ymax>
      </bndbox>
   </object>
   <object>
      <name>Suppliesr</name>
      <degree>91.51</degree>
      <direction>bt</direction>
      <bndbox>
         <xmin>14</xmin>
         <ymin>250</ymin>
         <xmax>40</xmax>
         <ymax>327</ymax>
      </bndbox>
   </object>
   <object>
      <name>Process</name>
      <degree>-0.52</degree>
      <direction>lr</direction>
      <bndbox>
         <xmin>596</xmin>
         <ymin>265</ymin>
         <xmax>650</xmax>
         <ymax>280</ymax>
      </bndbox>
   </object>
   <object>
      <name>Send</name>
      <degree>-0.0</degree>
      <direction>lr</direction>
      <bndbox>
         <xmin>264</xmin>
         <ymin>263</ymin>
         <xmax>313</xmax>
         <ymax>280</ymax>
      </bndbox>
   </object>
   <object>
      <name>prepare</name>
      <degree>2.2</degree>
      <direction>lr</direction>
      <bndbox>
         <xmin>134</xmin>
         <ymin>264</ymin>
         <xmax>205</xmax>
         <ymax>282</ymax>
      </bndbox>
   </object>
   <object>
      <name>change</name>
      <degree>0.72</degree>
      <direction>lr</direction>
      <bndbox>
         <xmin>473</xmin>
         <ymin>239</ymin>
         <xmax>514</xmax>
         <ymax>253</ymax>
      </bndbox>
   </object>
   <object>
      <name>confirmation</name>
      <degree>-0.0</degree>
      <direction>lr</direction>
      <bndbox>
         <xmin>669</xmin>
         <ymin>222</ymin>
         <xmax>757</xmax>
         <ymax>235</ymax>
      </bndbox>
   </object>
   <object>
      <name>order</name>
      <degree>0.64</degree>
      <direction>lr</direction>
      <bndbox>
         <xmin>558</xmin>
         <ymin>223</ymin>
         <xmax>604</xmax>
         <ymax>235</ymax>
      </bndbox>
   </object>
   <object>
      <name>order</name>
      <degree>2.86</degree>
      <direction>lr</direction>
      <bndbox>
         <xmin>462</xmin>
         <ymin>229</ymin>
         <xmax>506</xmax>
         <ymax>243</ymax>
      </bndbox>
   </object>
   <object>
      <name>ask</name>
      <degree>-0.0</degree>
      <direction>lr</direction>
      <bndbox>
         <xmin>673</xmin>
         <ymin>208</ymin>
         <xmax>704</xmax>
         <ymax>222</ymax>
      </bndbox>
   </object>
   <object>
      <name>update</name>
      <degree>0.55</degree>
      <direction>lr</direction>
      <bndbox>
         <xmin>561</xmin>
         <ymin>207</ymin>
         <xmax>609</xmax>
         <ymax>220</ymax>
      </bndbox>
   </object>
   <object>
      <name>response</name>
      <degree>-0.9</degree>
      <direction>lr</direction>
      <bndbox>
         <xmin>513</xmin>
         <ymin>147</ymin>
         <xmax>579</xmax>
         <ymax>164</ymax>
      </bndbox>
   </object>
   <object>
      <name>no</name>
      <degree>-0.0</degree>
      <direction>lr</direction>
      <bndbox>
         <xmin>487</xmin>
         <ymin>146</ymin>
         <xmax>507</xmax>
         <ymax>162</ymax>
      </bndbox>
   </object>
   <object>
      <name>give</name>
      <degree>-0.0</degree>
      <direction>lr</direction>
      <bndbox>
         <xmin>447</xmin>
         <ymin>147</ymin>
         <xmax>487</xmax>
         <ymax>163</ymax>
      </bndbox>
   </object>
   <object>
      <name>retailer</name>
      <degree>90.36</degree>
      <direction>bt</direction>
      <bndbox>
         <xmin>12</xmin>
         <ymin>105</ymin>
         <xmax>39</xmax>
         <ymax>189</ymax>
      </bndbox>
   </object>
   <object>
      <name>change</name>
      <degree>-1.1</degree>
      <direction>lr</direction>
      <bndbox>
         <xmin>514</xmin>
         <ymin>117</ymin>
         <xmax>567</xmax>
         <ymax>135</ymax>
      </bndbox>
   </object>
   <object>
      <name>request</name>
      <degree>1.36</degree>
      <direction>lr</direction>
      <bndbox>
         <xmin>444</xmin>
         <ymin>117</ymin>
         <xmax>512</xmax>
         <ymax>134</ymax>
      </bndbox>
   </object>
   <object>
      <name>request</name>
      <degree>0.85</degree>
      <direction>lr</direction>
      <bndbox>
         <xmin>238</xmin>
         <ymin>118</ymin>
         <xmax>310</xmax>
         <ymax>132</ymax>
      </bndbox>
   </object>
   <object>
      <name>order</name>
      <degree>0.68</degree>
      <direction>lr</direction>
      <bndbox>
         <xmin>524</xmin>
         <ymin>85</ymin>
         <xmax>563</xmax>
         <ymax>101</ymax>
      </bndbox>
   </object>
   <object>
      <name>confirm</name>
      <degree>0</degree>
      <direction>lr</direction>
      <bndbox>
         <xmin>449</xmin>
         <ymin>86</ymin>
         <xmax>522</xmax>
         <ymax>102</ymax>
      </bndbox>
   </object>
</annotation>
