<?xml version="1.0" ?>
<annotation>
   <folder>ex01</folder>
   <filename>ex01_writer0077.jpg</filename>
   <size>
      <width>2481</width>
      <height>3509</height>
   </size>
   <object>
      <name>accepted</name>
      <degree>1.03</degree>
      <direction>lr</direction>
      <bndbox>
         <xmin>1050</xmin>
         <ymin>2932</ymin>
         <xmax>1324</xmax>
         <ymax>3014</ymax>
      </bndbox>
   </object>
   <object>
      <name>request</name>
      <degree>-2.06</degree>
      <direction>lr</direction>
      <bndbox>
         <xmin>1268</xmin>
         <ymin>2859</ymin>
         <xmax>1485</xmax>
         <ymax>2954</ymax>
      </bndbox>
   </object>
   <object>
      <name>Credit</name>
      <degree>-0.73</degree>
      <direction>lr</direction>
      <bndbox>
         <xmin>1052</xmin>
         <ymin>2851</ymin>
         <xmax>1239</xmax>
         <ymax>2932</ymax>
      </bndbox>
   </object>
   <object>
      <name>results</name>
      <degree>0.13</degree>
      <direction>lr</direction>
      <bndbox>
         <xmin>408</xmin>
         <ymin>2280</ymin>
         <xmax>632</xmax>
         <ymax>2355</ymax>
      </bndbox>
   </object>
   <object>
      <name>disbursement</name>
      <degree>-0.38</degree>
      <direction>lr</direction>
      <bndbox>
         <xmin>1285</xmin>
         <ymin>2227</ymin>
         <xmax>1680</xmax>
         <ymax>2304</ymax>
      </bndbox>
   </object>
   <object>
      <name>with</name>
      <degree>4.67</degree>
      <direction>lr</direction>
      <bndbox>
         <xmin>614</xmin>
         <ymin>2204</ymin>
         <xmax>740</xmax>
         <ymax>2278</ymax>
      </bndbox>
   </object>
   <object>
      <name>customer</name>
      <degree>0.49</degree>
      <direction>lr</direction>
      <bndbox>
         <xmin>358</xmin>
         <ymin>2217</ymin>
         <xmax>594</xmax>
         <ymax>2288</ymax>
      </bndbox>
   </object>
   <object>
      <name>Organise</name>
      <degree>-1.77</degree>
      <direction>lr</direction>
      <bndbox>
         <xmin>1338</xmin>
         <ymin>2152</ymin>
         <xmax>1617</xmax>
         <ymax>2238</ymax>
      </bndbox>
   </object>
   <object>
      <name>Notify</name>
      <degree>-2.95</degree>
      <direction>lr</direction>
      <bndbox>
         <xmin>427</xmin>
         <ymin>2141</ymin>
         <xmax>645</xmax>
         <ymax>2237</ymax>
      </bndbox>
   </object>
   <object>
      <name>risk</name>
      <degree>-0.0</degree>
      <direction>lr</direction>
      <bndbox>
         <xmin>666</xmin>
         <ymin>1220</ymin>
         <xmax>764</xmax>
         <ymax>1290</ymax>
      </bndbox>
   </object>
   <object>
      <name>advanced</name>
      <degree>1.49</degree>
      <direction>lr</direction>
      <bndbox>
         <xmin>412</xmin>
         <ymin>1218</ymin>
         <xmax>637</xmax>
         <ymax>1290</ymax>
      </bndbox>
   </object>
   <object>
      <name>Assess</name>
      <degree>-2.53</degree>
      <direction>lr</direction>
      <bndbox>
         <xmin>451</xmin>
         <ymin>1130</ymin>
         <xmax>714</xmax>
         <ymax>1224</ymax>
      </bndbox>
   </object>
   <object>
      <name>threshold</name>
      <degree>1.25</degree>
      <direction>lr</direction>
      <bndbox>
         <xmin>1311</xmin>
         <ymin>759</ymin>
         <xmax>1553</xmax>
         <ymax>840</ymax>
      </bndbox>
   </object>
   <object>
      <name>beneath</name>
      <degree>2.09</degree>
      <direction>lr</direction>
      <bndbox>
         <xmin>1088</xmin>
         <ymin>776</ymin>
         <xmax>1279</xmax>
         <ymax>840</ymax>
      </bndbox>
   </object>
   <object>
      <name>risk</name>
      <degree>0.85</degree>
      <direction>lr</direction>
      <bndbox>
         <xmin>1104</xmin>
         <ymin>705</ymin>
         <xmax>1252</xmax>
         <ymax>777</ymax>
      </bndbox>
   </object>
   <object>
      <name>threshold</name>
      <degree>0.82</degree>
      <direction>lr</direction>
      <bndbox>
         <xmin>751</xmin>
         <ymin>739</ymin>
         <xmax>952</xmax>
         <ymax>808</ymax>
      </bndbox>
   </object>
   <object>
      <name>above</name>
      <degree>-0.0</degree>
      <direction>lr</direction>
      <bndbox>
         <xmin>589</xmin>
         <ymin>743</ymin>
         <xmax>732</xmax>
         <ymax>807</ymax>
      </bndbox>
   </object>
   <object>
      <name>risk</name>
      <degree>2.45</degree>
      <direction>lr</direction>
      <bndbox>
         <xmin>632</xmin>
         <ymin>675</ymin>
         <xmax>779</xmax>
         <ymax>747</ymax>
      </bndbox>
   </object>
   <object>
      <name>risk</name>
      <degree>0</degree>
      <direction>lr</direction>
      <bndbox>
         <xmin>919</xmin>
         <ymin>492</ymin>
         <xmax>1107</xmax>
         <ymax>580</ymax>
      </bndbox>
   </object>
   <object>
      <name>Assess</name>
      <degree>-0.99</degree>
      <direction>lr</direction>
      <bndbox>
         <xmin>884</xmin>
         <ymin>427</ymin>
         <xmax>1135</xmax>
         <ymax>516</ymax>
      </bndbox>
   </object>
   <object>
      <name>received</name>
      <degree>-0.68</degree>
      <direction>lr</direction>
      <bndbox>
         <xmin>1172</xmin>
         <ymin>142</ymin>
         <xmax>1439</xmax>
         <ymax>219</ymax>
      </bndbox>
   </object>
   <object>
      <name>request</name>
      <degree>-1.19</degree>
      <direction>lr</direction>
      <bndbox>
         <xmin>1373</xmin>
         <ymin>73</ymin>
         <xmax>1598</xmax>
         <ymax>167</ymax>
      </bndbox>
   </object>
   <object>
      <name>Credit</name>
      <degree>0</degree>
      <direction>lr</direction>
      <bndbox>
         <xmin>1160</xmin>
         <ymin>74</ymin>
         <xmax>1349</xmax>
         <ymax>154</ymax>
      </bndbox>
   </object>
</annotation>
