<?xml version="1.0" ?>
<annotation>
   <folder>ex03</folder>
   <filename>ex03_writer0031.jpg</filename>
   <size>
      <width>1600</width>
      <height>1200</height>
   </size>
   <object>
      <name>claimant</name>
      <degree>0</degree>
      <direction>lr</direction>
      <bndbox>
         <xmin>640</xmin>
         <ymin>105</ymin>
         <xmax>803</xmax>
         <ymax>156</ymax>
      </bndbox>
   </object>
   <object>
      <name>insurance</name>
      <degree>3.4</degree>
      <direction>lr</direction>
      <bndbox>
         <xmin>425</xmin>
         <ymin>274</ymin>
         <xmax>501</xmax>
         <ymax>294</ymax>
      </bndbox>
   </object>
   <object>
      <name>DB</name>
      <degree>5.08</degree>
      <direction>lr</direction>
      <bndbox>
         <xmin>443</xmin>
         <ymin>287</ymin>
         <xmax>472</xmax>
         <ymax>305</ymax>
      </bndbox>
   </object>
   <object>
      <name>claim</name>
      <degree>1.3</degree>
      <direction>lr</direction>
      <bndbox>
         <xmin>157</xmin>
         <ymin>324</ymin>
         <xmax>200</xmax>
         <ymax>340</ymax>
      </bndbox>
   </object>
   <object>
      <name>not</name>
      <degree>-0.73</degree>
      <direction>lr</direction>
      <bndbox>
         <xmin>597</xmin>
         <ymin>264</ymin>
         <xmax>641</xmax>
         <ymax>292</ymax>
      </bndbox>
   </object>
   <object>
      <name>insured</name>
      <degree>-0.0</degree>
      <direction>lr</direction>
      <bndbox>
         <xmin>639</xmin>
         <ymin>262</ymin>
         <xmax>700</xmax>
         <ymax>290</ymax>
      </bndbox>
   </object>
   <object>
      <name>reject</name>
      <degree>3.27</degree>
      <direction>lr</direction>
      <bndbox>
         <xmin>708</xmin>
         <ymin>271</ymin>
         <xmax>763</xmax>
         <ymax>298</ymax>
      </bndbox>
   </object>
   <object>
      <name>check</name>
      <degree>5.6</degree>
      <direction>lr</direction>
      <bndbox>
         <xmin>325</xmin>
         <ymin>321</ymin>
         <xmax>379</xmax>
         <ymax>348</ymax>
      </bndbox>
   </object>
   <object>
      <name>Claim</name>
      <degree>5.47</degree>
      <direction>lr</direction>
      <bndbox>
         <xmin>710</xmin>
         <ymin>295</ymin>
         <xmax>767</xmax>
         <ymax>318</ymax>
      </bndbox>
   </object>
   <object>
      <name>didnt</name>
      <degree>0</degree>
      <direction>lr</direction>
      <bndbox>
         <xmin>1327</xmin>
         <ymin>228</ymin>
         <xmax>1383</xmax>
         <ymax>250</ymax>
      </bndbox>
   </object>
   <object>
      <name>provide</name>
      <degree>0</degree>
      <direction>lr</direction>
      <bndbox>
         <xmin>1388</xmin>
         <ymin>229</ymin>
         <xmax>1444</xmax>
         <ymax>248</ymax>
      </bndbox>
   </object>
   <object>
      <name>claim</name>
      <degree>91.51</degree>
      <direction>bt</direction>
      <bndbox>
         <xmin>113</xmin>
         <ymin>361</ymin>
         <xmax>139</xmax>
         <ymax>433</ymax>
      </bndbox>
   </object>
   <object>
      <name>officer</name>
      <degree>89.49</degree>
      <direction>bt</direction>
      <bndbox>
         <xmin>113</xmin>
         <ymin>295</ymin>
         <xmax>137</xmax>
         <ymax>357</ymax>
      </bndbox>
   </object>
   <object>
      <name>claimant</name>
      <degree>8.05</degree>
      <direction>lr</direction>
      <bndbox>
         <xmin>324</xmin>
         <ymin>334</ymin>
         <xmax>428</xmax>
         <ymax>367</ymax>
      </bndbox>
   </object>
   <object>
      <name>check</name>
      <degree>5.65</degree>
      <direction>lr</direction>
      <bndbox>
         <xmin>1198</xmin>
         <ymin>253</ymin>
         <xmax>1248</xmax>
         <ymax>280</ymax>
      </bndbox>
   </object>
   <object>
      <name>correct</name>
      <degree>0</degree>
      <direction>lr</direction>
      <bndbox>
         <xmin>1317</xmin>
         <ymin>252</ymin>
         <xmax>1366</xmax>
         <ymax>266</ymax>
      </bndbox>
   </object>
   <object>
      <name>information</name>
      <degree>0</degree>
      <direction>lr</direction>
      <bndbox>
         <xmin>1367</xmin>
         <ymin>249</ymin>
         <xmax>1446</xmax>
         <ymax>259</ymax>
      </bndbox>
   </object>
   <object>
      <name>for</name>
      <degree>8.47</degree>
      <direction>lr</direction>
      <bndbox>
         <xmin>1200</xmin>
         <ymin>281</ymin>
         <xmax>1227</xmax>
         <ymax>300</ymax>
      </bndbox>
   </object>
   <object>
      <name>inform</name>
      <degree>1.03</degree>
      <direction>lr</direction>
      <bndbox>
         <xmin>1450</xmin>
         <ymin>247</ymin>
         <xmax>1515</xmax>
         <ymax>268</ymax>
      </bndbox>
   </object>
   <object>
      <name>claim</name>
      <degree>4.4</degree>
      <direction>lr</direction>
      <bndbox>
         <xmin>198</xmin>
         <ymin>385</ymin>
         <xmax>257</xmax>
         <ymax>413</ymax>
      </bndbox>
   </object>
   <object>
      <name>completeness</name>
      <degree>7.87</degree>
      <direction>lr</direction>
      <bndbox>
         <xmin>1198</xmin>
         <ymin>289</ymin>
         <xmax>1290</xmax>
         <ymax>322</ymax>
      </bndbox>
   </object>
   <object>
      <name>recieved</name>
      <degree>4.64</degree>
      <direction>lr</direction>
      <bndbox>
         <xmin>202</xmin>
         <ymin>408</ymin>
         <xmax>283</xmax>
         <ymax>436</ymax>
      </bndbox>
   </object>
   <object>
      <name>insured</name>
      <degree>8.13</degree>
      <direction>lr</direction>
      <bndbox>
         <xmin>562</xmin>
         <ymin>373</ymin>
         <xmax>641</xmax>
         <ymax>407</ymax>
      </bndbox>
   </object>
   <object>
      <name>provide</name>
      <degree>8.82</degree>
      <direction>lr</direction>
      <bndbox>
         <xmin>1376</xmin>
         <ymin>313</ymin>
         <xmax>1438</xmax>
         <ymax>343</ymax>
      </bndbox>
   </object>
   <object>
      <name>updated</name>
      <degree>4.61</degree>
      <direction>lr</direction>
      <bndbox>
         <xmin>1284</xmin>
         <ymin>339</ymin>
         <xmax>1349</xmax>
         <ymax>362</ymax>
      </bndbox>
   </object>
   <object>
      <name>forms</name>
      <degree>1.13</degree>
      <direction>lr</direction>
      <bndbox>
         <xmin>1287</xmin>
         <ymin>358</ymin>
         <xmax>1341</xmax>
         <ymax>374</ymax>
      </bndbox>
   </object>
   <object>
      <name>call</name>
      <degree>5.6</degree>
      <direction>lr</direction>
      <bndbox>
         <xmin>1379</xmin>
         <ymin>336</ymin>
         <xmax>1406</xmax>
         <ymax>359</ymax>
      </bndbox>
   </object>
   <object>
      <name>relevant</name>
      <degree>3.25</degree>
      <direction>lr</direction>
      <bndbox>
         <xmin>1407</xmin>
         <ymin>330</ymin>
         <xmax>1484</xmax>
         <ymax>356</ymax>
      </bndbox>
   </object>
   <object>
      <name>information</name>
      <degree>2.27</degree>
      <direction>lr</direction>
      <bndbox>
         <xmin>1382</xmin>
         <ymin>353</ymin>
         <xmax>1493</xmax>
         <ymax>372</ymax>
      </bndbox>
   </object>
   <object>
      <name>evaluate</name>
      <degree>5.31</degree>
      <direction>lr</direction>
      <bndbox>
         <xmin>514</xmin>
         <ymin>492</ymin>
         <xmax>598</xmax>
         <ymax>521</ymax>
      </bndbox>
   </object>
   <object>
      <name>severity</name>
      <degree>3.96</degree>
      <direction>lr</direction>
      <bndbox>
         <xmin>503</xmin>
         <ymin>518</ymin>
         <xmax>587</xmax>
         <ymax>547</ymax>
      </bndbox>
   </object>
   <object>
      <name>senior</name>
      <degree>0</degree>
      <direction>lr</direction>
      <bndbox>
         <xmin>108</xmin>
         <ymin>584</ymin>
         <xmax>133</xmax>
         <ymax>650</ymax>
      </bndbox>
   </object>
   <object>
      <name>claims</name>
      <degree>0</degree>
      <direction>lr</direction>
      <bndbox>
         <xmin>110</xmin>
         <ymin>505</ymin>
         <xmax>138</xmax>
         <ymax>574</ymax>
      </bndbox>
   </object>
   <object>
      <name>officer</name>
      <degree>90.35</degree>
      <direction>bt</direction>
      <bndbox>
         <xmin>137</xmin>
         <ymin>543</ymin>
         <xmax>164</xmax>
         <ymax>629</ymax>
      </bndbox>
   </object>
   <object>
      <name>claim</name>
      <degree>11.09</degree>
      <direction>lr</direction>
      <bndbox>
         <xmin>359</xmin>
         <ymin>567</ymin>
         <xmax>425</xmax>
         <ymax>604</ymax>
      </bndbox>
   </object>
   <object>
      <name>of</name>
      <degree>2.6</degree>
      <direction>lr</direction>
      <bndbox>
         <xmin>504</xmin>
         <ymin>549</ymin>
         <xmax>531</xmax>
         <ymax>572</ymax>
      </bndbox>
   </object>
   <object>
      <name>claim</name>
      <degree>3.58</degree>
      <direction>lr</direction>
      <bndbox>
         <xmin>534</xmin>
         <ymin>546</ymin>
         <xmax>602</xmax>
         <ymax>570</ymax>
      </bndbox>
   </object>
   <object>
      <name>send</name>
      <degree>4.76</degree>
      <direction>lr</direction>
      <bndbox>
         <xmin>1037</xmin>
         <ymin>641</ymin>
         <xmax>1093</xmax>
         <ymax>670</ymax>
      </bndbox>
   </object>
   <object>
      <name>get</name>
      <degree>5.96</degree>
      <direction>lr</direction>
      <bndbox>
         <xmin>1155</xmin>
         <ymin>631</ymin>
         <xmax>1194</xmax>
         <ymax>664</ymax>
      </bndbox>
   </object>
   <object>
      <name>updated</name>
      <degree>5.89</degree>
      <direction>lr</direction>
      <bndbox>
         <xmin>1197</xmin>
         <ymin>625</ymin>
         <xmax>1280</xmax>
         <ymax>657</ymax>
      </bndbox>
   </object>
   <object>
      <name>send</name>
      <degree>10.04</degree>
      <direction>lr</direction>
      <bndbox>
         <xmin>705</xmin>
         <ymin>690</ymin>
         <xmax>761</xmax>
         <ymax>724</ymax>
      </bndbox>
   </object>
   <object>
      <name>automatic</name>
      <degree>5.95</degree>
      <direction>lr</direction>
      <bndbox>
         <xmin>762</xmin>
         <ymin>678</ymin>
         <xmax>867</xmax>
         <ymax>715</ymax>
      </bndbox>
   </object>
   <object>
      <name>claim</name>
      <degree>7.05</degree>
      <direction>lr</direction>
      <bndbox>
         <xmin>906</xmin>
         <ymin>672</ymin>
         <xmax>968</xmax>
         <ymax>700</ymax>
      </bndbox>
   </object>
   <object>
      <name>relevant</name>
      <degree>7.75</degree>
      <direction>lr</direction>
      <bndbox>
         <xmin>1023</xmin>
         <ymin>660</ymin>
         <xmax>1113</xmax>
         <ymax>697</ymax>
      </bndbox>
   </object>
   <object>
      <name>insurer</name>
      <degree>0</degree>
      <direction>lr</direction>
      <bndbox>
         <xmin>38</xmin>
         <ymin>720</ymin>
         <xmax>73</xmax>
         <ymax>839</ymax>
      </bndbox>
   </object>
   <object>
      <name>notification</name>
      <degree>7.25</degree>
      <direction>lr</direction>
      <bndbox>
         <xmin>723</xmin>
         <ymin>710</ymin>
         <xmax>839</xmax>
         <ymax>751</ymax>
      </bndbox>
   </object>
   <object>
      <name>forms</name>
      <degree>3.58</degree>
      <direction>lr</direction>
      <bndbox>
         <xmin>1024</xmin>
         <ymin>696</ymin>
         <xmax>1093</xmax>
         <ymax>724</ymax>
      </bndbox>
   </object>
   <object>
      <name>forms</name>
      <degree>8.97</degree>
      <direction>lr</direction>
      <bndbox>
         <xmin>1167</xmin>
         <ymin>668</ymin>
         <xmax>1231</xmax>
         <ymax>705</ymax>
      </bndbox>
   </object>
   <object>
      <name>updated</name>
      <degree>4.34</degree>
      <direction>lr</direction>
      <bndbox>
         <xmin>1313</xmin>
         <ymin>660</ymin>
         <xmax>1385</xmax>
         <ymax>688</ymax>
      </bndbox>
   </object>
   <object>
      <name>System</name>
      <degree>92.31</degree>
      <direction>bt</direction>
      <bndbox>
         <xmin>126</xmin>
         <ymin>759</ymin>
         <xmax>156</xmax>
         <ymax>832</ymax>
      </bndbox>
   </object>
   <object>
      <name>SAP</name>
      <degree>88.84</degree>
      <direction>bt</direction>
      <bndbox>
         <xmin>95</xmin>
         <ymin>774</ymin>
         <xmax>122</xmax>
         <ymax>823</ymax>
      </bndbox>
   </object>
   <object>
      <name>claim</name>
      <degree>8.47</degree>
      <direction>lr</direction>
      <bndbox>
         <xmin>609</xmin>
         <ymin>751</ymin>
         <xmax>663</xmax>
         <ymax>779</ymax>
      </bndbox>
   </object>
   <object>
      <name>forms</name>
      <degree>3.34</degree>
      <direction>lr</direction>
      <bndbox>
         <xmin>1307</xmin>
         <ymin>690</ymin>
         <xmax>1373</xmax>
         <ymax>717</ymax>
      </bndbox>
   </object>
   <object>
      <name>forms</name>
      <degree>6.93</degree>
      <direction>lr</direction>
      <bndbox>
         <xmin>904</xmin>
         <ymin>744</ymin>
         <xmax>951</xmax>
         <ymax>768</ymax>
      </bndbox>
   </object>
   <object>
      <name>DB</name>
      <degree>4.48</degree>
      <direction>lr</direction>
      <bndbox>
         <xmin>952</xmin>
         <ymin>742</ymin>
         <xmax>975</xmax>
         <ymax>764</ymax>
      </bndbox>
   </object>
   <object>
      <name>register</name>
      <degree>3.73</degree>
      <direction>lr</direction>
      <bndbox>
         <xmin>1328</xmin>
         <ymin>862</ymin>
         <xmax>1420</xmax>
         <ymax>898</ymax>
      </bndbox>
   </object>
   <object>
      <name>claims</name>
      <degree>88.02</degree>
      <direction>bt</direction>
      <bndbox>
         <xmin>85</xmin>
         <ymin>1039</ymin>
         <xmax>122</xmax>
         <ymax>1149</ymax>
      </bndbox>
   </object>
   <object>
      <name>Management</name>
      <degree>86.42</degree>
      <direction>bt</direction>
      <bndbox>
         <xmin>88</xmin>
         <ymin>893</ymin>
         <xmax>130</xmax>
         <ymax>1019</ymax>
      </bndbox>
   </object>
   <object>
      <name>claim</name>
      <degree>4.05</degree>
      <direction>lr</direction>
      <bndbox>
         <xmin>1324</xmin>
         <ymin>903</ymin>
         <xmax>1402</xmax>
         <ymax>932</ymax>
      </bndbox>
   </object>
   <object>
      <name>system</name>
      <degree>90.0</degree>
      <direction>bt</direction>
      <bndbox>
         <xmin>129</xmin>
         <ymin>1001</ymin>
         <xmax>160</xmax>
         <ymax>1092</ymax>
      </bndbox>
   </object>
   <object>
      <name>process</name>
      <degree>4.09</degree>
      <direction>lr</direction>
      <bndbox>
         <xmin>1524</xmin>
         <ymin>914</ymin>
         <xmax>1598</xmax>
         <ymax>941</ymax>
      </bndbox>
   </object>
   <object>
      <name>claim</name>
      <degree>5.09</degree>
      <direction>lr</direction>
      <bndbox>
         <xmin>1145</xmin>
         <ymin>961</ymin>
         <xmax>1207</xmax>
         <ymax>992</ymax>
      </bndbox>
   </object>
   <object>
      <name>ended</name>
      <degree>2.12</degree>
      <direction>lr</direction>
      <bndbox>
         <xmin>1521</xmin>
         <ymin>940</ymin>
         <xmax>1598</xmax>
         <ymax>966</ymax>
      </bndbox>
   </object>
   <object>
      <name>(approved)</name>
      <degree>8.55</degree>
      <direction>lr</direction>
      <bndbox>
         <xmin>1125</xmin>
         <ymin>987</ymin>
         <xmax>1227</xmax>
         <ymax>1034</ymax>
      </bndbox>
   </object>
   <object>
      <name>claim</name>
      <degree>1.15</degree>
      <direction>lr</direction>
      <bndbox>
         <xmin>1293</xmin>
         <ymin>1057</ymin>
         <xmax>1355</xmax>
         <ymax>1081</ymax>
      </bndbox>
   </object>
   <object>
      <name>DB</name>
      <degree>-1.02</degree>
      <direction>lr</direction>
      <bndbox>
         <xmin>1358</xmin>
         <ymin>1057</ymin>
         <xmax>1386</xmax>
         <ymax>1082</ymax>
      </bndbox>
   </object>
   <object>
      <name>reject</name>
      <degree>0</degree>
      <direction>lr</direction>
      <bndbox>
         <xmin>673</xmin>
         <ymin>771</ymin>
         <xmax>722</xmax>
         <ymax>789</ymax>
      </bndbox>
   </object>
   <object>
      <name>notification</name>
      <degree>0</degree>
      <direction>lr</direction>
      <bndbox>
         <xmin>655</xmin>
         <ymin>788</ymin>
         <xmax>745</xmax>
         <ymax>807</ymax>
      </bndbox>
   </object>
   <object>
      <name>insured</name>
      <degree>5.71</degree>
      <direction>lr</direction>
      <bndbox>
         <xmin>321</xmin>
         <ymin>361</ymin>
         <xmax>406</xmax>
         <ymax>384</ymax>
      </bndbox>
   </object>
</annotation>
