<?xml version="1.0" ?>
<annotation>
   <folder>ex08</folder>
   <filename>ex08_writer0095.jpg</filename>
   <size>
      <width>4054</width>
      <height>2568</height>
   </size>
   <object>
      <name>register</name>
      <degree>0</degree>
      <direction>lr</direction>
      <bndbox>
         <xmin>747</xmin>
         <ymin>165</ymin>
         <xmax>1067</xmax>
         <ymax>268</ymax>
      </bndbox>
   </object>
   <object>
      <name>wait</name>
      <degree>1.5</degree>
      <direction>lr</direction>
      <bndbox>
         <xmin>1305</xmin>
         <ymin>132</ymin>
         <xmax>1462</xmax>
         <ymax>206</ymax>
      </bndbox>
   </object>
   <object>
      <name>for</name>
      <degree>-0.49</degree>
      <direction>lr</direction>
      <bndbox>
         <xmin>1504</xmin>
         <ymin>105</ymin>
         <xmax>1653</xmax>
         <ymax>202</ymax>
      </bndbox>
   </object>
   <object>
      <name>the</name>
      <degree>2.24</degree>
      <direction>lr</direction>
      <bndbox>
         <xmin>1300</xmin>
         <ymin>219</ymin>
         <xmax>1418</xmax>
         <ymax>297</ymax>
      </bndbox>
   </object>
   <object>
      <name>results</name>
      <degree>2.03</degree>
      <direction>lr</direction>
      <bndbox>
         <xmin>1448</xmin>
         <ymin>206</ymin>
         <xmax>1734</xmax>
         <ymax>292</ymax>
      </bndbox>
   </object>
   <object>
      <name>school</name>
      <degree>1.78</degree>
      <direction>lr</direction>
      <bndbox>
         <xmin>2216</xmin>
         <ymin>245</ymin>
         <xmax>2463</xmax>
         <ymax>346</ymax>
      </bndbox>
   </object>
   <object>
      <name>year</name>
      <degree>1.45</degree>
      <direction>lr</direction>
      <bndbox>
         <xmin>2477</xmin>
         <ymin>241</ymin>
         <xmax>2645</xmax>
         <ymax>370</ymax>
      </bndbox>
   </object>
   <object>
      <name>organized</name>
      <degree>0.96</degree>
      <direction>lr</direction>
      <bndbox>
         <xmin>2667</xmin>
         <ymin>217</ymin>
         <xmax>3051</xmax>
         <ymax>342</ymax>
      </bndbox>
   </object>
   <object>
      <name>booking</name>
      <degree>-1.2</degree>
      <direction>lr</direction>
      <bndbox>
         <xmin>446</xmin>
         <ymin>332</ymin>
         <xmax>694</xmax>
         <ymax>435</ymax>
      </bndbox>
   </object>
   <object>
      <name>courses</name>
      <degree>2.74</degree>
      <direction>lr</direction>
      <bndbox>
         <xmin>760</xmin>
         <ymin>278</ymin>
         <xmax>1089</xmax>
         <ymax>360</ymax>
      </bndbox>
   </object>
   <object>
      <name>opened</name>
      <degree>-1.4</degree>
      <direction>lr</direction>
      <bndbox>
         <xmin>479</xmin>
         <ymin>441</ymin>
         <xmax>666</xmax>
         <ymax>510</ymax>
      </bndbox>
   </object>
   <object>
      <name>Students</name>
      <degree>88.3</degree>
      <direction>bt</direction>
      <bndbox>
         <xmin>300</xmin>
         <ymin>242</ymin>
         <xmax>406</xmax>
         <ymax>579</ymax>
      </bndbox>
   </object>
   <object>
      <name>indirect</name>
      <degree>0.62</degree>
      <direction>lr</direction>
      <bndbox>
         <xmin>1108</xmin>
         <ymin>638</ymin>
         <xmax>1388</xmax>
         <ymax>727</ymax>
      </bndbox>
   </object>
   <object>
      <name>communication</name>
      <degree>-1.32</degree>
      <direction>lr</direction>
      <bndbox>
         <xmin>1404</xmin>
         <ymin>655</ymin>
         <xmax>1774</xmax>
         <ymax>736</ymax>
      </bndbox>
   </object>
   <object>
      <name>through</name>
      <degree>-2.97</degree>
      <direction>lr</direction>
      <bndbox>
         <xmin>1784</xmin>
         <ymin>663</ymin>
         <xmax>1951</xmax>
         <ymax>747</ymax>
      </bndbox>
   </object>
   <object>
      <name>software</name>
      <degree>-4.18</degree>
      <direction>lr</direction>
      <bndbox>
         <xmin>1961</xmin>
         <ymin>671</ymin>
         <xmax>2176</xmax>
         <ymax>764</ymax>
      </bndbox>
   </object>
   <object>
      <name>Enter</name>
      <degree>1.44</degree>
      <direction>lr</direction>
      <bndbox>
         <xmin>865</xmin>
         <ymin>886</ymin>
         <xmax>1045</xmax>
         <ymax>967</ymax>
      </bndbox>
   </object>
   <object>
      <name>information</name>
      <degree>0.55</degree>
      <direction>lr</direction>
      <bndbox>
         <xmin>1071</xmin>
         <ymin>861</ymin>
         <xmax>1374</xmax>
         <ymax>958</ymax>
      </bndbox>
   </object>
   <object>
      <name>week</name>
      <degree>3.8</degree>
      <direction>lr</direction>
      <bndbox>
         <xmin>1468</xmin>
         <ymin>821</ymin>
         <xmax>1618</xmax>
         <ymax>899</ymax>
      </bndbox>
   </object>
   <object>
      <name>before</name>
      <degree>3.24</degree>
      <direction>lr</direction>
      <bndbox>
         <xmin>1625</xmin>
         <ymin>792</ymin>
         <xmax>1799</xmax>
         <ymax>890</ymax>
      </bndbox>
   </object>
   <object>
      <name>school</name>
      <degree>8.31</degree>
      <direction>lr</direction>
      <bndbox>
         <xmin>1643</xmin>
         <ymin>874</ymin>
         <xmax>1808</xmax>
         <ymax>950</ymax>
      </bndbox>
   </object>
   <object>
      <name>starts</name>
      <degree>4.87</degree>
      <direction>lr</direction>
      <bndbox>
         <xmin>1811</xmin>
         <ymin>856</ymin>
         <xmax>1994</xmax>
         <ymax>929</ymax>
      </bndbox>
   </object>
   <object>
      <name>in</name>
      <degree>-0.0</degree>
      <direction>lr</direction>
      <bndbox>
         <xmin>897</xmin>
         <ymin>970</ymin>
         <xmax>989</xmax>
         <ymax>1058</ymax>
      </bndbox>
   </object>
   <object>
      <name>CBS</name>
      <degree>-0.14</degree>
      <direction>lr</direction>
      <bndbox>
         <xmin>1004</xmin>
         <ymin>968</ymin>
         <xmax>1205</xmax>
         <ymax>1061</ymax>
      </bndbox>
   </object>
   <object>
      <name>send</name>
      <degree>2.78</degree>
      <direction>lr</direction>
      <bndbox>
         <xmin>1856</xmin>
         <ymin>947</ymin>
         <xmax>2013</xmax>
         <ymax>1017</ymax>
      </bndbox>
   </object>
   <object>
      <name>students</name>
      <degree>3.03</degree>
      <direction>lr</direction>
      <bndbox>
         <xmin>2030</xmin>
         <ymin>932</ymin>
         <xmax>2241</xmax>
         <ymax>1011</ymax>
      </bndbox>
   </object>
   <object>
      <name>wait</name>
      <degree>-0.0</degree>
      <direction>lr</direction>
      <bndbox>
         <xmin>2591</xmin>
         <ymin>925</ymin>
         <xmax>2755</xmax>
         <ymax>1002</ymax>
      </bndbox>
   </object>
   <object>
      <name>descriptions</name>
      <degree>-2.49</degree>
      <direction>lr</direction>
      <bndbox>
         <xmin>489</xmin>
         <ymin>1019</ymin>
         <xmax>788</xmax>
         <ymax>1141</ymax>
      </bndbox>
   </object>
   <object>
      <name>lists</name>
      <degree>3.14</degree>
      <direction>lr</direction>
      <bndbox>
         <xmin>1866</xmin>
         <ymin>1042</ymin>
         <xmax>2017</xmax>
         <ymax>1130</ymax>
      </bndbox>
   </object>
   <object>
      <name>to</name>
      <degree>2.62</degree>
      <direction>lr</direction>
      <bndbox>
         <xmin>2043</xmin>
         <ymin>1040</ymin>
         <xmax>2114</xmax>
         <ymax>1118</ymax>
      </bndbox>
   </object>
   <object>
      <name>teachers</name>
      <degree>0.13</degree>
      <direction>lr</direction>
      <bndbox>
         <xmin>2112</xmin>
         <ymin>1037</ymin>
         <xmax>2329</xmax>
         <ymax>1115</ymax>
      </bndbox>
   </object>
   <object>
      <name>for</name>
      <degree>-1.34</degree>
      <direction>lr</direction>
      <bndbox>
         <xmin>2606</xmin>
         <ymin>1010</ymin>
         <xmax>2715</xmax>
         <ymax>1085</ymax>
      </bndbox>
   </object>
   <object>
      <name>rebook</name>
      <degree>2.88</degree>
      <direction>lr</direction>
      <bndbox>
         <xmin>3025</xmin>
         <ymin>985</ymin>
         <xmax>3226</xmax>
         <ymax>1057</ymax>
      </bndbox>
   </object>
   <object>
      <name>recieved</name>
      <degree>-2.1</degree>
      <direction>lr</direction>
      <bndbox>
         <xmin>517</xmin>
         <ymin>1149</ymin>
         <xmax>753</xmax>
         <ymax>1227</ymax>
      </bndbox>
   </object>
   <object>
      <name>Lists</name>
      <degree>-1.13</degree>
      <direction>lr</direction>
      <bndbox>
         <xmin>2557</xmin>
         <ymin>1091</ymin>
         <xmax>2712</xmax>
         <ymax>1162</ymax>
      </bndbox>
   </object>
   <object>
      <name>to</name>
      <degree>-3.09</degree>
      <direction>lr</direction>
      <bndbox>
         <xmin>2722</xmin>
         <ymin>1098</ymin>
         <xmax>2781</xmax>
         <ymax>1165</ymax>
      </bndbox>
   </object>
   <object>
      <name>come</name>
      <degree>-4.54</degree>
      <direction>lr</direction>
      <bndbox>
         <xmin>2792</xmin>
         <ymin>1102</ymin>
         <xmax>2934</xmax>
         <ymax>1176</ymax>
      </bndbox>
   </object>
   <object>
      <name>students</name>
      <degree>3.36</degree>
      <direction>lr</direction>
      <bndbox>
         <xmin>3013</xmin>
         <ymin>1043</ymin>
         <xmax>3317</xmax>
         <ymax>1128</ymax>
      </bndbox>
   </object>
   <object>
      <name>back</name>
      <degree>-0.62</degree>
      <direction>lr</direction>
      <bndbox>
         <xmin>2754</xmin>
         <ymin>1170</ymin>
         <xmax>2895</xmax>
         <ymax>1227</ymax>
      </bndbox>
   </object>
   <object>
      <name>in</name>
      <degree>1.58</degree>
      <direction>lr</direction>
      <bndbox>
         <xmin>3022</xmin>
         <ymin>1128</ymin>
         <xmax>3096</xmax>
         <ymax>1195</ymax>
      </bndbox>
   </object>
   <object>
      <name>CBS</name>
      <degree>0.72</degree>
      <direction>lr</direction>
      <bndbox>
         <xmin>3131</xmin>
         <ymin>1122</ymin>
         <xmax>3293</xmax>
         <ymax>1196</ymax>
      </bndbox>
   </object>
   <object>
      <name>send</name>
      <degree>-1.44</degree>
      <direction>lr</direction>
      <bndbox>
         <xmin>3016</xmin>
         <ymin>1289</ymin>
         <xmax>3197</xmax>
         <ymax>1357</ymax>
      </bndbox>
   </object>
   <object>
      <name>class</name>
      <degree>1.23</degree>
      <direction>lr</direction>
      <bndbox>
         <xmin>3463</xmin>
         <ymin>1238</ymin>
         <xmax>3675</xmax>
         <ymax>1318</ymax>
      </bndbox>
   </object>
   <object>
      <name>the</name>
      <degree>-1.85</degree>
      <direction>lr</direction>
      <bndbox>
         <xmin>2967</xmin>
         <ymin>1351</ymin>
         <xmax>3079</xmax>
         <ymax>1423</ymax>
      </bndbox>
   </object>
   <object>
      <name>Students</name>
      <degree>1.07</degree>
      <direction>lr</direction>
      <bndbox>
         <xmin>3090</xmin>
         <ymin>1348</ymin>
         <xmax>3333</xmax>
         <ymax>1423</ymax>
      </bndbox>
   </object>
   <object>
      <name>organized</name>
      <degree>1.94</degree>
      <direction>lr</direction>
      <bndbox>
         <xmin>3571</xmin>
         <ymin>1297</ymin>
         <xmax>3971</xmax>
         <ymax>1397</ymax>
      </bndbox>
   </object>
   <object>
      <name>Secretary</name>
      <degree>87.33</degree>
      <direction>bt</direction>
      <bndbox>
         <xmin>212</xmin>
         <ymin>990</ymin>
         <xmax>352</xmax>
         <ymax>1409</ymax>
      </bndbox>
   </object>
   <object>
      <name>classes</name>
      <degree>-1.65</degree>
      <direction>lr</direction>
      <bndbox>
         <xmin>2862</xmin>
         <ymin>1417</ymin>
         <xmax>3090</xmax>
         <ymax>1505</ymax>
      </bndbox>
   </object>
   <object>
      <name>info</name>
      <degree>-2.16</degree>
      <direction>lr</direction>
      <bndbox>
         <xmin>3105</xmin>
         <ymin>1428</ymin>
         <xmax>3252</xmax>
         <ymax>1508</ymax>
      </bndbox>
   </object>
   <object>
      <name>Lists</name>
      <degree>5.47</degree>
      <direction>lr</direction>
      <bndbox>
         <xmin>2064</xmin>
         <ymin>1509</ymin>
         <xmax>2236</xmax>
         <ymax>1620</ymax>
      </bndbox>
   </object>
   <object>
      <name>Hand</name>
      <degree>-0.22</degree>
      <direction>lr</direction>
      <bndbox>
         <xmin>3487</xmin>
         <ymin>1480</ymin>
         <xmax>3622</xmax>
         <ymax>1603</ymax>
      </bndbox>
   </object>
   <object>
      <name>deliverd</name>
      <degree>0.27</degree>
      <direction>lr</direction>
      <bndbox>
         <xmin>3634</xmin>
         <ymin>1480</ymin>
         <xmax>3871</xmax>
         <ymax>1603</ymax>
      </bndbox>
   </object>
   <object>
      <name>list</name>
      <degree>1.01</degree>
      <direction>lr</direction>
      <bndbox>
         <xmin>3857</xmin>
         <ymin>1477</ymin>
         <xmax>4002</xmax>
         <ymax>1601</ymax>
      </bndbox>
   </object>
   <object>
      <name>Onemonth</name>
      <degree>0.73</degree>
      <direction>lr</direction>
      <bndbox>
         <xmin>606</xmin>
         <ymin>1629</ymin>
         <xmax>898</xmax>
         <ymax>1690</ymax>
      </bndbox>
   </object>
   <object>
      <name>before</name>
      <degree>2.88</degree>
      <direction>lr</direction>
      <bndbox>
         <xmin>781</xmin>
         <ymin>1671</ymin>
         <xmax>943</xmax>
         <ymax>1737</ymax>
      </bndbox>
   </object>
   <object>
      <name>year</name>
      <degree>4.11</degree>
      <direction>lr</direction>
      <bndbox>
         <xmin>951</xmin>
         <ymin>1661</ymin>
         <xmax>1057</xmax>
         <ymax>1736</ymax>
      </bndbox>
   </object>
   <object>
      <name>starts</name>
      <degree>5.07</degree>
      <direction>lr</direction>
      <bndbox>
         <xmin>1066</xmin>
         <ymin>1647</ymin>
         <xmax>1237</xmax>
         <ymax>1729</ymax>
      </bndbox>
   </object>
   <object>
      <name>descriptions</name>
      <degree>2.83</degree>
      <direction>lr</direction>
      <bndbox>
         <xmin>1337</xmin>
         <ymin>1621</ymin>
         <xmax>1666</xmax>
         <ymax>1711</ymax>
      </bndbox>
   </object>
   <object>
      <name>recieve</name>
      <degree>-1.39</degree>
      <direction>lr</direction>
      <bndbox>
         <xmin>1911</xmin>
         <ymin>1652</ymin>
         <xmax>2161</xmax>
         <ymax>1714</ymax>
      </bndbox>
   </object>
   <object>
      <name>list</name>
      <degree>-2.83</degree>
      <direction>lr</direction>
      <bndbox>
         <xmin>2188</xmin>
         <ymin>1653</ymin>
         <xmax>2343</xmax>
         <ymax>1728</ymax>
      </bndbox>
   </object>
   <object>
      <name>forward</name>
      <degree>-0.0</degree>
      <direction>lr</direction>
      <bndbox>
         <xmin>1016</xmin>
         <ymin>1748</ymin>
         <xmax>1252</xmax>
         <ymax>1834</ymax>
      </bndbox>
   </object>
   <object>
      <name>of</name>
      <degree>-1.85</degree>
      <direction>lr</direction>
      <bndbox>
         <xmin>2055</xmin>
         <ymin>1707</ymin>
         <xmax>2128</xmax>
         <ymax>1766</ymax>
      </bndbox>
   </object>
   <object>
      <name>students</name>
      <degree>1.71</degree>
      <direction>lr</direction>
      <bndbox>
         <xmin>2135</xmin>
         <ymin>1692</ymin>
         <xmax>2408</xmax>
         <ymax>1766</ymax>
      </bndbox>
   </object>
   <object>
      <name>courses</name>
      <degree>0.65</degree>
      <direction>lr</direction>
      <bndbox>
         <xmin>1017</xmin>
         <ymin>1839</ymin>
         <xmax>1238</xmax>
         <ymax>1900</ymax>
      </bndbox>
   </object>
   <object>
      <name>descriptions</name>
      <degree>-0.52</degree>
      <direction>lr</direction>
      <bndbox>
         <xmin>1058</xmin>
         <ymin>1894</ymin>
         <xmax>1405</xmax>
         <ymax>1961</ymax>
      </bndbox>
   </object>
   <object>
      <name>too</name>
      <degree>0.67</degree>
      <direction>lr</direction>
      <bndbox>
         <xmin>2049</xmin>
         <ymin>1894</ymin>
         <xmax>2136</xmax>
         <ymax>1947</ymax>
      </bndbox>
   </object>
   <object>
      <name>List</name>
      <degree>4.64</degree>
      <direction>lr</direction>
      <bndbox>
         <xmin>3437</xmin>
         <ymin>1831</ymin>
         <xmax>3562</xmax>
         <ymax>1919</ymax>
      </bndbox>
   </object>
   <object>
      <name>many</name>
      <degree>5.0</degree>
      <direction>lr</direction>
      <bndbox>
         <xmin>2033</xmin>
         <ymin>1945</ymin>
         <xmax>2158</xmax>
         <ymax>2004</ymax>
      </bndbox>
   </object>
   <object>
      <name>choose</name>
      <degree>1.35</degree>
      <direction>lr</direction>
      <bndbox>
         <xmin>2624</xmin>
         <ymin>1928</ymin>
         <xmax>2839</xmax>
         <ymax>1990</ymax>
      </bndbox>
   </object>
   <object>
      <name>Students?</name>
      <degree>-2.69</degree>
      <direction>lr</direction>
      <bndbox>
         <xmin>1995</xmin>
         <ymin>2021</ymin>
         <xmax>2253</xmax>
         <ymax>2103</ymax>
      </bndbox>
   </object>
   <object>
      <name>Yes</name>
      <degree>-7.28</degree>
      <direction>lr</direction>
      <bndbox>
         <xmin>2327</xmin>
         <ymin>2032</ymin>
         <xmax>2445</xmax>
         <ymax>2129</ymax>
      </bndbox>
   </object>
   <object>
      <name>students</name>
      <degree>-1.99</degree>
      <direction>lr</direction>
      <bndbox>
         <xmin>2609</xmin>
         <ymin>1991</ymin>
         <xmax>2857</xmax>
         <ymax>2057</ymax>
      </bndbox>
   </object>
   <object>
      <name>over</name>
      <degree>-1.62</degree>
      <direction>lr</direction>
      <bndbox>
         <xmin>2882</xmin>
         <ymin>1999</ymin>
         <xmax>3011</xmax>
         <ymax>2060</ymax>
      </bndbox>
   </object>
   <object>
      <name>Send</name>
      <degree>0.81</degree>
      <direction>lr</direction>
      <bndbox>
         <xmin>3181</xmin>
         <ymin>1950</ymin>
         <xmax>3324</xmax>
         <ymax>2016</ymax>
      </bndbox>
   </object>
   <object>
      <name>Priority</name>
      <degree>-1.87</degree>
      <direction>lr</direction>
      <bndbox>
         <xmin>2659</xmin>
         <ymin>2057</ymin>
         <xmax>3008</xmax>
         <ymax>2162</ymax>
      </bndbox>
   </object>
   <object>
      <name>list</name>
      <degree>-2.47</degree>
      <direction>lr</direction>
      <bndbox>
         <xmin>3189</xmin>
         <ymin>2014</ymin>
         <xmax>3367</xmax>
         <ymax>2092</ymax>
      </bndbox>
   </object>
   <object>
      <name>back</name>
      <degree>1.28</degree>
      <direction>lr</direction>
      <bndbox>
         <xmin>3211</xmin>
         <ymin>2092</ymin>
         <xmax>3391</xmax>
         <ymax>2166</ymax>
      </bndbox>
   </object>
   <object>
      <name>class</name>
      <degree>-0.0</degree>
      <direction>lr</direction>
      <bndbox>
         <xmin>3568</xmin>
         <ymin>2129</ymin>
         <xmax>3740</xmax>
         <ymax>2200</ymax>
      </bndbox>
   </object>
   <object>
      <name>ready</name>
      <degree>1.64</degree>
      <direction>lr</direction>
      <bndbox>
         <xmin>3560</xmin>
         <ymin>2197</ymin>
         <xmax>3737</xmax>
         <ymax>2271</ymax>
      </bndbox>
   </object>
   <object>
      <name>teachers</name>
      <degree>88.18</degree>
      <direction>bt</direction>
      <bndbox>
         <xmin>387</xmin>
         <ymin>1910</ymin>
         <xmax>490</xmax>
         <ymax>2323</ymax>
      </bndbox>
   </object>
   <object>
      <name>for</name>
      <degree>2.3</degree>
      <direction>lr</direction>
      <bndbox>
         <xmin>3565</xmin>
         <ymin>2278</ymin>
         <xmax>3668</xmax>
         <ymax>2353</ymax>
      </bndbox>
   </object>
   <object>
      <name>school</name>
      <degree>3.15</degree>
      <direction>lr</direction>
      <bndbox>
         <xmin>3551</xmin>
         <ymin>2354</ymin>
         <xmax>3745</xmax>
         <ymax>2431</ymax>
      </bndbox>
   </object>
   <object>
      <name>and</name>
      <degree>0</degree>
      <direction>lr</direction>
      <bndbox>
         <xmin>3015</xmin>
         <ymin>1195</ymin>
         <xmax>3220</xmax>
         <ymax>1277</ymax>
      </bndbox>
   </object>
   <object>
      <name>NO</name>
      <degree>0</degree>
      <direction>lr</direction>
      <bndbox>
         <xmin>2239</xmin>
         <ymin>1763</ymin>
         <xmax>2329</xmax>
         <ymax>1831</ymax>
      </bndbox>
   </object>
</annotation>
