<?xml version="1.0" ?>
<annotation>
   <folder>ex00</folder>
   <filename>ex00_writer0104.jpg</filename>
   <size>
      <width>2185</width>
      <height>1585</height>
   </size>
   <object>
      <name>number</name>
      <degree>-0.73</degree>
      <direction>lr</direction>
      <bndbox>
         <xmin>1533</xmin>
         <ymin>796</ymin>
         <xmax>1649</xmax>
         <ymax>831</ymax>
      </bndbox>
   </object>
   <object>
      <name>PIN</name>
      <degree>-1.75</degree>
      <direction>lr</direction>
      <bndbox>
         <xmin>1470</xmin>
         <ymin>799</ymin>
         <xmax>1531</xmax>
         <ymax>827</ymax>
      </bndbox>
   </object>
   <object>
      <name>send</name>
      <degree>-0.36</degree>
      <direction>lr</direction>
      <bndbox>
         <xmin>1507</xmin>
         <ymin>761</ymin>
         <xmax>1592</xmax>
         <ymax>798</ymax>
      </bndbox>
   </object>
   <object>
      <name>approved</name>
      <degree>1.6</degree>
      <direction>lr</direction>
      <bndbox>
         <xmin>642</xmin>
         <ymin>685</ymin>
         <xmax>805</xmax>
         <ymax>731</ymax>
      </bndbox>
   </object>
   <object>
      <name>is</name>
      <degree>-1.91</degree>
      <direction>lr</direction>
      <bndbox>
         <xmin>599</xmin>
         <ymin>689</ymin>
         <xmax>642</xmax>
         <ymax>726</ymax>
      </bndbox>
   </object>
   <object>
      <name>card</name>
      <degree>0.73</degree>
      <direction>lr</direction>
      <bndbox>
         <xmin>1535</xmin>
         <ymin>649</ymin>
         <xmax>1621</xmax>
         <ymax>680</ymax>
      </bndbox>
   </object>
   <object>
      <name>bank</name>
      <degree>-0.0</degree>
      <direction>lr</direction>
      <bndbox>
         <xmin>1440</xmin>
         <ymin>651</ymin>
         <xmax>1519</xmax>
         <ymax>679</ymax>
      </bndbox>
   </object>
   <object>
      <name>account</name>
      <degree>0.5</degree>
      <direction>lr</direction>
      <bndbox>
         <xmin>956</xmin>
         <ymin>653</ymin>
         <xmax>1063</xmax>
         <ymax>682</ymax>
      </bndbox>
   </object>
   <object>
      <name>bank</name>
      <degree>-1.59</degree>
      <direction>lr</direction>
      <bndbox>
         <xmin>871</xmin>
         <ymin>653</ymin>
         <xmax>953</xmax>
         <ymax>683</ymax>
      </bndbox>
   </object>
   <object>
      <name>application</name>
      <degree>2.57</degree>
      <direction>lr</direction>
      <bndbox>
         <xmin>604</xmin>
         <ymin>648</ymin>
         <xmax>789</xmax>
         <ymax>694</ymax>
      </bndbox>
   </object>
   <object>
      <name>send</name>
      <degree>-2.65</degree>
      <direction>lr</direction>
      <bndbox>
         <xmin>1502</xmin>
         <ymin>610</ymin>
         <xmax>1593</xmax>
         <ymax>653</ymax>
      </bndbox>
   </object>
   <object>
      <name>new</name>
      <degree>-0.95</degree>
      <direction>lr</direction>
      <bndbox>
         <xmin>983</xmin>
         <ymin>615</ymin>
         <xmax>1057</xmax>
         <ymax>649</ymax>
      </bndbox>
   </object>
   <object>
      <name>create</name>
      <degree>0.58</degree>
      <direction>lr</direction>
      <bndbox>
         <xmin>870</xmin>
         <ymin>614</ymin>
         <xmax>975</xmax>
         <ymax>648</ymax>
      </bndbox>
   </object>
   <object>
      <name>received</name>
      <degree>-0.4</degree>
      <direction>lr</direction>
      <bndbox>
         <xmin>54</xmin>
         <ymin>613</ymin>
         <xmax>216</xmax>
         <ymax>650</ymax>
      </bndbox>
   </object>
   <object>
      <name>application</name>
      <degree>0.46</degree>
      <direction>lr</direction>
      <bndbox>
         <xmin>51</xmin>
         <ymin>571</ymin>
         <xmax>251</xmax>
         <ymax>615</ymax>
      </bndbox>
   </object>
   <object>
      <name>online</name>
      <degree>0.54</degree>
      <direction>lr</direction>
      <bndbox>
         <xmin>67</xmin>
         <ymin>535</ymin>
         <xmax>178</xmax>
         <ymax>574</ymax>
      </bndbox>
   </object>
   <object>
      <name>pack</name>
      <degree>-0.0</degree>
      <direction>lr</direction>
      <bndbox>
         <xmin>1543</xmin>
         <ymin>497</ymin>
         <xmax>1625</xmax>
         <ymax>527</ymax>
      </bndbox>
   </object>
   <object>
      <name>welcome</name>
      <degree>-0.57</degree>
      <direction>lr</direction>
      <bndbox>
         <xmin>1432</xmin>
         <ymin>495</ymin>
         <xmax>1536</xmax>
         <ymax>523</ymax>
      </bndbox>
   </object>
   <object>
      <name>application</name>
      <degree>0.89</degree>
      <direction>lr</direction>
      <bndbox>
         <xmin>346</xmin>
         <ymin>493</ymin>
         <xmax>509</xmax>
         <ymax>529</ymax>
      </bndbox>
   </object>
   <object>
      <name>send</name>
      <degree>-0.39</degree>
      <direction>lr</direction>
      <bndbox>
         <xmin>1489</xmin>
         <ymin>461</ymin>
         <xmax>1578</xmax>
         <ymax>497</ymax>
      </bndbox>
   </object>
   <object>
      <name>evaluate</name>
      <degree>-0.0</degree>
      <direction>lr</direction>
      <bndbox>
         <xmin>357</xmin>
         <ymin>462</ymin>
         <xmax>498</xmax>
         <ymax>497</ymax>
      </bndbox>
   </object>
   <object>
      <name>customer</name>
      <degree>0.8</degree>
      <direction>lr</direction>
      <bndbox>
         <xmin>866</xmin>
         <ymin>353</ymin>
         <xmax>1014</xmax>
         <ymax>383</ymax>
      </bndbox>
   </object>
   <object>
      <name>notify</name>
      <degree>-1.6</degree>
      <direction>lr</direction>
      <bndbox>
         <xmin>878</xmin>
         <ymin>311</ymin>
         <xmax>997</xmax>
         <ymax>359</ymax>
      </bndbox>
   </object>
   <object>
      <name>rejected</name>
      <degree>1.03</degree>
      <direction>lr</direction>
      <bndbox>
         <xmin>649</xmin>
         <ymin>315</ymin>
         <xmax>762</xmax>
         <ymax>353</ymax>
      </bndbox>
   </object>
   <object>
      <name>is</name>
      <degree>-0.0</degree>
      <direction>lr</direction>
      <bndbox>
         <xmin>609</xmin>
         <ymin>317</ymin>
         <xmax>645</xmax>
         <ymax>353</ymax>
      </bndbox>
   </object>
   <object>
      <name>application</name>
      <degree>0</degree>
      <direction>lr</direction>
      <bndbox>
         <xmin>617</xmin>
         <ymin>275</ymin>
         <xmax>785</xmax>
         <ymax>313</ymax>
      </bndbox>
   </object>
</annotation>
